{
  "name": "moonbitlang/core/uint16",
  "traits": [],
  "types": [],
  "typealias": [],
  "values": [
    {
      "name": "max_value",
      "docstring": "",
      "signature": "let max_value : UInt16",
      "loc": {
        "path": "moonbitlang/core/uint16",
        "file": "uint16.mbt",
        "line": 16,
        "column": 9
      }
    },
    {
      "name": "min_value",
      "docstring": "",
      "signature": "let min_value : UInt16",
      "loc": {
        "path": "moonbitlang/core/uint16",
        "file": "uint16.mbt",
        "line": 19,
        "column": 9
      }
    }
  ],
  "misc": [
    {
      "name": "UInt16",
      "impls": [
        {
          "self": { "name": "UInt16", "path": "moonbitlang/core/uint16" },
          "trait": { "name": "Add", "path": "moonbitlang/core/builtin" },
          "methods": [
            {
              "name": "op_add",
              "docstring": "",
              "signature": "fn op_add(self : UInt16, that : UInt16) -> UInt16",
              "loc": {
                "path": "moonbitlang/core/uint16",
                "file": "uint16.mbt",
                "line": 22,
                "column": 30
              }
            }
          ]
        },
        {
          "self": { "name": "UInt16", "path": "moonbitlang/core/uint16" },
          "trait": { "name": "BitAnd", "path": "moonbitlang/core/builtin" },
          "methods": [
            {
              "name": "land",
              "docstring": "",
              "signature": "fn land(self : UInt16, that : UInt16) -> UInt16",
              "loc": {
                "path": "moonbitlang/core/uint16",
                "file": "uint16.mbt",
                "line": 77,
                "column": 33
              }
            }
          ]
        },
        {
          "self": { "name": "UInt16", "path": "moonbitlang/core/uint16" },
          "trait": { "name": "BitOr", "path": "moonbitlang/core/builtin" },
          "methods": [
            {
              "name": "lor",
              "docstring": "",
              "signature": "fn lor(self : UInt16, that : UInt16) -> UInt16",
              "loc": {
                "path": "moonbitlang/core/uint16",
                "file": "uint16.mbt",
                "line": 72,
                "column": 32
              }
            }
          ]
        },
        {
          "self": { "name": "UInt16", "path": "moonbitlang/core/uint16" },
          "trait": { "name": "BitXOr", "path": "moonbitlang/core/builtin" },
          "methods": [
            {
              "name": "lxor",
              "docstring": "",
              "signature": "fn lxor(self : UInt16, that : UInt16) -> UInt16",
              "loc": {
                "path": "moonbitlang/core/uint16",
                "file": "uint16.mbt",
                "line": 82,
                "column": 33
              }
            }
          ]
        },
        {
          "self": { "name": "UInt16", "path": "moonbitlang/core/uint16" },
          "trait": { "name": "Compare", "path": "moonbitlang/core/builtin" },
          "methods": [
            {
              "name": "compare",
              "docstring": "",
              "signature": "fn compare(self : UInt16, that : UInt16) -> Int",
              "loc": {
                "path": "moonbitlang/core/uint16",
                "file": "uint16.mbt",
                "line": 47,
                "column": 34
              }
            }
          ]
        },
        {
          "self": { "name": "UInt16", "path": "moonbitlang/core/uint16" },
          "trait": { "name": "Default", "path": "moonbitlang/core/builtin" },
          "methods": [
            {
              "name": "default",
              "docstring": "",
              "signature": "fn default() -> UInt16",
              "loc": {
                "path": "moonbitlang/core/uint16",
                "file": "uint16.mbt",
                "line": 87,
                "column": 34
              }
            }
          ]
        },
        {
          "self": { "name": "UInt16", "path": "moonbitlang/core/uint16" },
          "trait": { "name": "Div", "path": "moonbitlang/core/builtin" },
          "methods": [
            {
              "name": "op_div",
              "docstring": "",
              "signature": "fn op_div(self : UInt16, that : UInt16) -> UInt16",
              "loc": {
                "path": "moonbitlang/core/uint16",
                "file": "uint16.mbt",
                "line": 37,
                "column": 30
              }
            }
          ]
        },
        {
          "self": { "name": "UInt16", "path": "moonbitlang/core/uint16" },
          "trait": { "name": "Eq", "path": "moonbitlang/core/builtin" },
          "methods": [
            {
              "name": "op_equal",
              "docstring": "",
              "signature": "fn op_equal(self : UInt16, that : UInt16) -> Bool",
              "loc": {
                "path": "moonbitlang/core/uint16",
                "file": "uint16.mbt",
                "line": 42,
                "column": 29
              }
            }
          ]
        },
        {
          "self": { "name": "UInt16", "path": "moonbitlang/core/uint16" },
          "trait": { "name": "Hash", "path": "moonbitlang/core/builtin" },
          "methods": [
            {
              "name": "hash",
              "docstring": "",
              "signature": "fn hash(self : UInt16) -> Int",
              "loc": {
                "path": "moonbitlang/core/uint16",
                "file": "uint16.mbt",
                "line": 52,
                "column": 31
              }
            },
            {
              "name": "hash_combine",
              "docstring": "",
              "signature": "fn hash_combine(self : UInt16, hasher : <a href=\"moonbitlang/core/builtin#Hasher\">Hasher</a>) -> Unit",
              "loc": {
                "path": "moonbitlang/core/uint16",
                "file": "uint16.mbt",
                "line": 57,
                "column": 31
              }
            }
          ]
        },
        {
          "self": { "name": "UInt16", "path": "moonbitlang/core/uint16" },
          "trait": { "name": "Mul", "path": "moonbitlang/core/builtin" },
          "methods": [
            {
              "name": "op_mul",
              "docstring": "",
              "signature": "fn op_mul(self : UInt16, that : UInt16) -> UInt16",
              "loc": {
                "path": "moonbitlang/core/uint16",
                "file": "uint16.mbt",
                "line": 32,
                "column": 30
              }
            }
          ]
        },
        {
          "self": { "name": "UInt16", "path": "moonbitlang/core/uint16" },
          "trait": { "name": "Shl", "path": "moonbitlang/core/builtin" },
          "methods": [
            {
              "name": "op_shl",
              "docstring": "",
              "signature": "fn op_shl(self : UInt16, that : Int) -> UInt16",
              "loc": {
                "path": "moonbitlang/core/uint16",
                "file": "uint16.mbt",
                "line": 62,
                "column": 30
              }
            }
          ]
        },
        {
          "self": { "name": "UInt16", "path": "moonbitlang/core/uint16" },
          "trait": { "name": "Shr", "path": "moonbitlang/core/builtin" },
          "methods": [
            {
              "name": "op_shr",
              "docstring": "",
              "signature": "fn op_shr(self : UInt16, that : Int) -> UInt16",
              "loc": {
                "path": "moonbitlang/core/uint16",
                "file": "uint16.mbt",
                "line": 67,
                "column": 30
              }
            }
          ]
        },
        {
          "self": { "name": "UInt16", "path": "moonbitlang/core/uint16" },
          "trait": { "name": "Sub", "path": "moonbitlang/core/builtin" },
          "methods": [
            {
              "name": "op_sub",
              "docstring": "",
              "signature": "fn op_sub(self : UInt16, that : UInt16) -> UInt16",
              "loc": {
                "path": "moonbitlang/core/uint16",
                "file": "uint16.mbt",
                "line": 27,
                "column": 30
              }
            }
          ]
        }
      ],
      "methods": []
    }
  ]
}